Metadata-Version: 2.1
Name: topsis-ishaan
Version: 1.0.0
Summary: A Python package to implement Topsis analysis
Home-page: UNKNOWN
Author: Ishaan Vijh
Author-email: ishaan.vijh@gmail.com
License: MIT
Platform: UNKNOWN
Classifier: License :: OSI Approved :: MIT License
Classifier: Programming Language :: Python :: 3
Classifier: Programming Language :: Python :: 3.7
